jekyll2nikola-0_0_1.dist-info/metadata.json
jekyll2nikola-0_0_1.dist-info/METADATA
jekyll2nikola-0_0_1.dist-info/WHEEL
jekyll2nikola-0_0_1.dist-info/RECORD
jekyll2nikola-0_0_1.dist-info/top_level.txt
jekyll2nikola-0_0_1.dist-info/DESCRIPTION.rst
jekyll2nikola/__init__.py
jekyll2nikola/jekyll2nikola.py
